yonder/_init_.py
yonder/yonder.py
yonder-1.1.dist-info/LICENSE
yonder-1.1.dist-info/METADATA
yonder-1.1.dist-info/WHEEL
yonder-1.1.dist-info/top_level.txt
yonder-1.1.dist-info/RECORD
