Metadata-Version: 2.1
Name: yonder
Version: 1.1
Summary: A python package for data denoising and reconstruction
Home-page: https://github.com/pengchzn/yonder
Author: Peng Chen
Author-email: pengchzn@gmail.com
License: UNKNOWN
Keywords: Astrostatistics techniques,Astronomy software,Astronomy data analysis
Platform: UNKNOWN
Classifier: Topic :: Scientific/Engineering
Classifier: License :: OSI Approved :: GNU Lesser General Public License v3 (LGPLv3)
Classifier: Programming Language :: Python :: 3
License-File: LICENSE
